enumfields/__init__.py
enumfields/admin.py
enumfields/enums.py
enumfields/fields.py
enumfields/forms.py
enumfields/drf/__init__.py
enumfields/drf/fields.py
enumfields/drf/serializers.py
django_enumfields2-3.0.2.dist-info/METADATA
django_enumfields2-3.0.2.dist-info/WHEEL
django_enumfields2-3.0.2.dist-info/licenses/LICENSE
django_enumfields2-3.0.2.dist-info/RECORD
