Metadata-Version: 2.1
Name: django-enumfields2
Version: 3.0.2
Summary: Real Python Enums for Django.
Project-URL: Homepage, https://github.com/akx/django-enumfields2
Project-URL: Issues, https://github.com/akx/django-enumfields2/issues
Author-email: HZDG <webmaster@hzdg.com>
Maintainer-email: Aarni Koskela <akx@iki.fi>
License-File: LICENSE
Classifier: Environment :: Web Environment
Classifier: Framework :: Django
Classifier: Intended Audience :: Developers
Classifier: License :: OSI Approved :: MIT License
Classifier: Operating System :: OS Independent
Classifier: Programming Language :: Python
Classifier: Programming Language :: Python :: 3
Classifier: Programming Language :: Python :: 3.7
Classifier: Programming Language :: Python :: 3.8
Classifier: Programming Language :: Python :: 3.9
Classifier: Programming Language :: Python :: 3.10
Classifier: Programming Language :: Python :: 3.11
Classifier: Topic :: Internet :: WWW/HTTP
Requires-Python: >=3.7
Requires-Dist: django>=3.2
